root_dir/__init__.py
root_dir/data_dir.py
root_dir/data_root.py
root_dir-0.1.0.dist-info/METADATA
root_dir-0.1.0.dist-info/WHEEL
root_dir-0.1.0.dist-info/top_level.txt
root_dir-0.1.0.dist-info/RECORD
