Metadata-Version: 2.1
Name: root-dir
Version: 0.1.0
Summary: Manage a hierarchy of directories - mostly for data storage and access
Author-email: Nicolas Deutschmann <deu@zurich.ibm.com>
Project-URL: repository, https://github.ibm.com/DEU/root_dir
Requires-Python: <3.11,>=3.7
Requires-Dist: liblog
Requires-Dist: environment-files
Requires-Dist: python-dotenv
Provides-Extra: dev
Requires-Dist: pytest ; extra == 'dev'
Requires-Dist: pytest-cov ; extra == 'dev'
Requires-Dist: black ; extra == 'dev'
Requires-Dist: flake8 ; extra == 'dev'
Requires-Dist: pep8-naming ; extra == 'dev'
Requires-Dist: sphinx ; extra == 'dev'
Requires-Dist: sphinx-autodoc-typehints ; extra == 'dev'
Requires-Dist: better-apidoc ; extra == 'dev'
Requires-Dist: six ; extra == 'dev'
Requires-Dist: sphinx-rtd-theme ; extra == 'dev'
Requires-Dist: myst-parser ; extra == 'dev'
Requires-Dist: sphinx-toolbox ; extra == 'dev'
Requires-Dist: python-semantic-release ; extra == 'dev'
Requires-Dist: setuptools (>=45) ; extra == 'dev'
Requires-Dist: setuptools-scm[toml] (>=6.2) ; extra == 'dev'
Requires-Dist: build ; extra == 'dev'
Provides-Extra: test
Requires-Dist: pytest ; extra == 'test'
Requires-Dist: pytest-cov ; extra == 'test'
